Metadata-Version: 2.1
Name: yanimage
Version: 1.0.4
Summary: Python module for searching, getting links and downloading images from Yandex images
Home-page: UNKNOWN
Author: Elieren
Author-email: kir102906@gmail.com
License: UNKNOWN
Platform: UNKNOWN
